kgt_rwalang-1.0.2.dist-info/licenses/LICENCE
rwalang/__init__.py
rwalang/config.py
rwalang/detector.py
rwalang/linguistic_features.py
rwalang/utils.py
rwalang/models/kinya_detector.joblib
tests/__init__.py
tests/test_detector.py
tests/test_linguistic_features.py
tests/test_package.py
tests/test_utils.py
kgt_rwalang-1.0.2.dist-info/METADATA
kgt_rwalang-1.0.2.dist-info/WHEEL
kgt_rwalang-1.0.2.dist-info/top_level.txt
kgt_rwalang-1.0.2.dist-info/RECORD
