Metadata-Version: 2.4
Name: kgt_rwalang
Version: 1.0.2
Summary: An enhanced language detector for Kinyarwanda
Home-page: https://github.com/kigalithm/rwalang
Author: Kigalithm Ltd.
Author-email: foss@kigalithm.com
Classifier: Programming Language :: Python :: 3
Classifier: License :: OSI Approved :: MIT License
Classifier: Operating System :: OS Independent
Classifier: Topic :: Text Processing :: Linguistic
Classifier: Topic :: Scientific/Engineering :: Artificial Intelligence
Classifier: Development Status :: 3 - Alpha
Requires-Python: >=3.7
License-File: LICENCE
Requires-Dist: scikit-learn>=1.6.1
Requires-Dist: numpy>=2.2.5
Requires-Dist: joblib>=1.5.0
Requires-Dist: pandas>=2.2.3
Dynamic: author
Dynamic: author-email
Dynamic: classifier
Dynamic: description
Dynamic: description-content-type
Dynamic: home-page
Dynamic: license-file
Dynamic: requires-dist
Dynamic: requires-python
Dynamic: summary
